grove_gps/__init__.py
grove_gps/__main__.py
grove_gps/grove_gps.py
location_calcs/__init__.py
location_calcs/__main__.py
location_calcs/location_calcs.py
groveGPS-1.0.2.dist-info/LICENSE
groveGPS-1.0.2.dist-info/METADATA
groveGPS-1.0.2.dist-info/WHEEL
groveGPS-1.0.2.dist-info/top_level.txt
groveGPS-1.0.2.dist-info/RECORD
