Metadata-Version: 2.1
Name: groveGPS
Version: 1.0.2
Summary: Connect to Grove GPS and perform calculations on GPS values
Home-page: https://github.com/Paolo-dono/Grove_GPS
Author: Paulus Jacobus de Bruyn
Author-email: mailforpaolo@yahoo.com
License: MIT
Platform: UNKNOWN
Classifier: License :: OSI Approved :: MIT License
Classifier: Programming Language :: Python :: 3
Classifier: Programming Language :: Python :: 3.7
Requires-Dist: pyserial
Requires-Dist: datetime
